chuk_tool_registry/core/__init_.py
chuk_tool_registry/core/exceptions.py
chuk_tool_registry/core/interface.py
chuk_tool_registry/core/metadata.py
chuk_tool_registry/core/provider.py
chuk_tool_registry/discovery/__init__.py
chuk_tool_registry/discovery/auto_register.py
chuk_tool_registry/discovery/decorators.py
chuk_tool_registry/providers/__init_.py
chuk_tool_registry/providers/memory.py
chuk_tool_registry-0.1.0.dist-info/METADATA
chuk_tool_registry-0.1.0.dist-info/WHEEL
chuk_tool_registry-0.1.0.dist-info/top_level.txt
chuk_tool_registry-0.1.0.dist-info/RECORD
