Metadata-Version: 2.4
Name: chuk-tool-registry
Version: 0.1.0
Summary: Async-native tool registry for discovery and metadata management
Requires-Python: >=3.11
Requires-Dist: asyncio>=3.4.3
Requires-Dist: pydantic>=2.11.7
